adansonia/__init__.py
adansonia/bigquery.py
adansonia/mails.py
adansonia/utils.py
adansonia-0.0.12.dist-info/LICENSE
adansonia-0.0.12.dist-info/METADATA
adansonia-0.0.12.dist-info/WHEEL
adansonia-0.0.12.dist-info/top_level.txt
adansonia-0.0.12.dist-info/RECORD
