Metadata-Version: 2.1
Name: adansonia
Version: 0.0.12
Summary: Utils package for common operations
Home-page: https://github.com/baobab-group/Adansonia
Author: mlabarrere
Author-email: mlabarrere@baobab.bz
License: UNKNOWN
Platform: UNKNOWN
Classifier: Programming Language :: Python :: 3
Classifier: License :: OSI Approved :: Apache Software License
Classifier: Operating System :: OS Independent
Classifier: Natural Language :: English
Requires-Dist: numpy
Requires-Dist: pandas
Requires-Dist: google-cloud-bigquery
Requires-Dist: google-api-python-client
Requires-Dist: google-auth-httplib2
Requires-Dist: google-auth-oauthlib
Requires-Dist: pyarrow
